odoo9_addon_account_analytic_parent-9.0.1.0.0-py2.7-nspkg.pth
odoo9_addon_account_analytic_parent-9.0.1.0.0.dist-info/DESCRIPTION.rst
odoo9_addon_account_analytic_parent-9.0.1.0.0.dist-info/METADATA
odoo9_addon_account_analytic_parent-9.0.1.0.0.dist-info/RECORD
odoo9_addon_account_analytic_parent-9.0.1.0.0.dist-info/WHEEL
odoo9_addon_account_analytic_parent-9.0.1.0.0.dist-info/metadata.json
odoo9_addon_account_analytic_parent-9.0.1.0.0.dist-info/namespace_packages.txt
odoo9_addon_account_analytic_parent-9.0.1.0.0.dist-info/top_level.txt
odoo_addons/account_analytic_parent/README.rst
odoo_addons/account_analytic_parent/__init__.py
odoo_addons/account_analytic_parent/__openerp__.py
odoo_addons/account_analytic_parent/models/__init__.py
odoo_addons/account_analytic_parent/models/account_analytic_account.py
odoo_addons/account_analytic_parent/static/description/icon.png
odoo_addons/account_analytic_parent/tests/__init__.py
odoo_addons/account_analytic_parent/tests/test_account_analytic_account.py
odoo_addons/account_analytic_parent/views/account_analytic_account_view.xml
